zwishh/__init__.py
zwishh/sdk/__init__.py
zwishh/sdk/base_client.py
zwishh/sdk/carts.py
zwishh/sdk/coupon.py
zwishh/sdk/delivery.py
zwishh/sdk/interactions.py
zwishh/sdk/orders.py
zwishh/sdk/sellers.py
zwishh/sdk/users.py
zwishh/utils/__inti__.py
zwishh/utils/security.py
zwishh-0.1.18.dist-info/licenses/LICENCE
zwishh-0.1.18.dist-info/METADATA
zwishh-0.1.18.dist-info/WHEEL
zwishh-0.1.18.dist-info/top_level.txt
zwishh-0.1.18.dist-info/RECORD
