Metadata-Version: 2.4
Name: zwishh
Version: 0.1.18
Summary: Internal utils and SDKs for Zwishh services
Author-email: Backend Team <dev@zwishh.com>
License: MIT
Requires-Python: >=3.11
License-File: LICENCE
Requires-Dist: httpx>=0.26
Requires-Dist: pydantic>=2.7
Requires-Dist: typing-extensions>=4.0
Requires-Dist: fastapi>=0.110
Requires-Dist: tenacity>=8.0
Provides-Extra: dev
Requires-Dist: pytest; extra == "dev"
Requires-Dist: pytest-asyncio; extra == "dev"
Requires-Dist: mypy; extra == "dev"
Requires-Dist: ruff; extra == "dev"
Requires-Dist: respx; extra == "dev"
Requires-Dist: pytest-cov; extra == "dev"
Dynamic: license-file
